[
  {
    "concept": "is_distorted",
    "diff_step": 5,
    "pos_gen_audio_samples": 1029,
    "neg_gen_audio_samples": 4893,
    "embed_model": "laion-clap",
    "class_model_type": "logistic",
    "class_model_train_acc": 0.803875,
    "class_model_test_acc": 0.8068333333333331,
    "acc": 0.55724417426545,
    "tpr": 0.6491739552964041,
    "tnr": 0.5379113018597991
  },
  {
    "concept": "is_distorted",
    "diff_step": 10,
    "pos_gen_audio_samples": 1029,
    "neg_gen_audio_samples": 4893,
    "embed_model": "laion-clap",
    "class_model_type": "logistic",
    "class_model_train_acc": 0.803875,
    "class_model_test_acc": 0.8068333333333331,
    "acc": 0.7136102668017561,
    "tpr": 0.6394557823129251,
    "tnr": 0.7292049867157161
  },
  {
    "concept": "is_distorted",
    "diff_step": 15,
    "pos_gen_audio_samples": 1029,
    "neg_gen_audio_samples": 4893,
    "embed_model": "laion-clap",
    "class_model_type": "logistic",
    "class_model_train_acc": 0.803875,
    "class_model_test_acc": 0.8068333333333331,
    "acc": 0.851063829787234,
    "tpr": 0.552964042759961,
    "tnr": 0.913754342938892
  },
  {
    "concept": "is_distorted",
    "diff_step": 20,
    "pos_gen_audio_samples": 1029,
    "neg_gen_audio_samples": 4893,
    "embed_model": "laion-clap",
    "class_model_type": "logistic",
    "class_model_train_acc": 0.803875,
    "class_model_test_acc": 0.8068333333333331,
    "acc": 0.868456602499155,
    "tpr": 0.6394557823129251,
    "tnr": 0.9166155732679331
  },
  {
    "concept": "is_distorted",
    "diff_step": 25,
    "pos_gen_audio_samples": 1029,
    "neg_gen_audio_samples": 4893,
    "embed_model": "laion-clap",
    "class_model_type": "logistic",
    "class_model_train_acc": 0.803875,
    "class_model_test_acc": 0.8068333333333331,
    "acc": 0.864910503208375,
    "tpr": 0.6375121477162291,
    "tnr": 0.912732474964234
  },
  {
    "concept": "is_distorted",
    "diff_step": 30,
    "pos_gen_audio_samples": 1029,
    "neg_gen_audio_samples": 4893,
    "embed_model": "laion-clap",
    "class_model_type": "logistic",
    "class_model_train_acc": 0.803875,
    "class_model_test_acc": 0.8068333333333331,
    "acc": 0.8588314758527521,
    "tpr": 0.6151603498542271,
    "tnr": 0.9100756182301241
  },
  {
    "concept": "is_distorted",
    "diff_step": 35,
    "pos_gen_audio_samples": 1029,
    "neg_gen_audio_samples": 4893,
    "embed_model": "laion-clap",
    "class_model_type": "logistic",
    "class_model_train_acc": 0.803875,
    "class_model_test_acc": 0.8068333333333331,
    "acc": 0.857480580884836,
    "tpr": 0.58114674441205,
    "tnr": 0.9155937052932761
  },
  {
    "concept": "is_distorted",
    "diff_step": 40,
    "pos_gen_audio_samples": 1029,
    "neg_gen_audio_samples": 4893,
    "embed_model": "laion-clap",
    "class_model_type": "logistic",
    "class_model_train_acc": 0.803875,
    "class_model_test_acc": 0.8068333333333331,
    "acc": 0.8578183046268151,
    "tpr": 0.574344023323615,
    "tnr": 0.91743306764766
  },
  {
    "concept": "is_distorted",
    "diff_step": 45,
    "pos_gen_audio_samples": 1029,
    "neg_gen_audio_samples": 4893,
    "embed_model": "laion-clap",
    "class_model_type": "logistic",
    "class_model_train_acc": 0.803875,
    "class_model_test_acc": 0.8068333333333331,
    "acc": 0.8571428571428571,
    "tpr": 0.576287657920311,
    "tnr": 0.91620682607807
  },
  {
    "concept": "is_distorted",
    "diff_step": 49,
    "pos_gen_audio_samples": 1029,
    "neg_gen_audio_samples": 4893,
    "embed_model": "laion-clap",
    "class_model_type": "logistic",
    "class_model_train_acc": 0.803875,
    "class_model_test_acc": 0.8068333333333331,
    "acc": 0.8571428571428571,
    "tpr": 0.5753158406219631,
    "tnr": 0.9164111996730021
  },
  {
    "concept": "is_distorted",
    "diff_step": 5,
    "pos_gen_audio_samples": 1029,
    "neg_gen_audio_samples": 4893,
    "embed_model": "laion-clap",
    "class_model_type": "svm",
    "class_model_train_acc": 0.9122500000000001,
    "class_model_test_acc": 0.8923333333333331,
    "acc": 0.432792975346166,
    "tpr": 0.7259475218658891,
    "tnr": 0.371142448395667
  },
  {
    "concept": "is_distorted",
    "diff_step": 10,
    "pos_gen_audio_samples": 1029,
    "neg_gen_audio_samples": 4893,
    "embed_model": "laion-clap",
    "class_model_type": "svm",
    "class_model_train_acc": 0.9122500000000001,
    "class_model_test_acc": 0.8923333333333331,
    "acc": 0.678318135764944,
    "tpr": 0.681243926141885,
    "tnr": 0.677702840792969
  },
  {
    "concept": "is_distorted",
    "diff_step": 15,
    "pos_gen_audio_samples": 1029,
    "neg_gen_audio_samples": 4893,
    "embed_model": "laion-clap",
    "class_model_type": "svm",
    "class_model_train_acc": 0.9122500000000001,
    "class_model_test_acc": 0.8923333333333331,
    "acc": 0.8635596082404591,
    "tpr": 0.5140913508260441,
    "tnr": 0.937052932761087
  },
  {
    "concept": "is_distorted",
    "diff_step": 20,
    "pos_gen_audio_samples": 1029,
    "neg_gen_audio_samples": 4893,
    "embed_model": "laion-clap",
    "class_model_type": "svm",
    "class_model_train_acc": 0.9122500000000001,
    "class_model_test_acc": 0.8923333333333331,
    "acc": 0.8887200270178991,
    "tpr": 0.535471331389698,
    "tnr": 0.963008379317392
  },
  {
    "concept": "is_distorted",
    "diff_step": 25,
    "pos_gen_audio_samples": 1029,
    "neg_gen_audio_samples": 4893,
    "embed_model": "laion-clap",
    "class_model_type": "svm",
    "class_model_train_acc": 0.9122500000000001,
    "class_model_test_acc": 0.8923333333333331,
    "acc": 0.8887200270178991,
    "tpr": 0.49562682215743403,
    "tnr": 0.971387696709585
  },
  {
    "concept": "is_distorted",
    "diff_step": 30,
    "pos_gen_audio_samples": 1029,
    "neg_gen_audio_samples": 4893,
    "embed_model": "laion-clap",
    "class_model_type": "svm",
    "class_model_train_acc": 0.9122500000000001,
    "class_model_test_acc": 0.8923333333333331,
    "acc": 0.885005065856129,
    "tpr": 0.45092322643343,
    "tnr": 0.976292662987941
  },
  {
    "concept": "is_distorted",
    "diff_step": 35,
    "pos_gen_audio_samples": 1029,
    "neg_gen_audio_samples": 4893,
    "embed_model": "laion-clap",
    "class_model_type": "svm",
    "class_model_train_acc": 0.9122500000000001,
    "class_model_test_acc": 0.8923333333333331,
    "acc": 0.88129010469436,
    "tpr": 0.42565597667638405,
    "tnr": 0.977110157367668
  },
  {
    "concept": "is_distorted",
    "diff_step": 40,
    "pos_gen_audio_samples": 1029,
    "neg_gen_audio_samples": 4893,
    "embed_model": "laion-clap",
    "class_model_type": "svm",
    "class_model_train_acc": 0.9122500000000001,
    "class_model_test_acc": 0.8923333333333331,
    "acc": 0.8819655521783181,
    "tpr": 0.42662779397473205,
    "tnr": 0.9777232781524621
  },
  {
    "concept": "is_distorted",
    "diff_step": 45,
    "pos_gen_audio_samples": 1029,
    "neg_gen_audio_samples": 4893,
    "embed_model": "laion-clap",
    "class_model_type": "svm",
    "class_model_train_acc": 0.9122500000000001,
    "class_model_test_acc": 0.8923333333333331,
    "acc": 0.8836541708882131,
    "tpr": 0.43343051506316804,
    "tnr": 0.9783363989372571
  },
  {
    "concept": "is_distorted",
    "diff_step": 49,
    "pos_gen_audio_samples": 1029,
    "neg_gen_audio_samples": 4893,
    "embed_model": "laion-clap",
    "class_model_type": "svm",
    "class_model_train_acc": 0.91225,
    "class_model_test_acc": 0.8923333333333333,
    "acc": 0.8817966903073287,
    "tpr": 0.42565597667638483,
    "tnr": 0.9777232781524627
  }
]